.gitignore
LICENSE
Makefile
README.md
requirements.txt
setup.py
logftz/__init__.py
logftz/log.py
logftz.egg-info/PKG-INFO
logftz.egg-info/SOURCES.txt
logftz.egg-info/dependency_links.txt
logftz.egg-info/requires.txt
logftz.egg-info/top_level.txt