Metadata-Version: 2.4
Name: logftz
Version: 3.0.0
Summary: A timezone-configurable logging package based on loguru with Shanghai timezone as default
Home-page: https://github.com/stdeson/logftz
Author: stdeson
Author-email: stdeson@gmail.com
Keywords: logging loguru timezone configurable international
Classifier: Development Status :: 4 - Beta
Classifier: Intended Audience :: Developers
Classifier: License :: OSI Approved :: MIT License
Classifier: Operating System :: OS Independent
Classifier: Programming Language :: Python :: 3
Classifier: Programming Language :: Python :: 3.7
Classifier: Programming Language :: Python :: 3.8
Classifier: Programming Language :: Python :: 3.9
Classifier: Programming Language :: Python :: 3.10
Classifier: Programming Language :: Python :: 3.11
Requires-Python: >=3.7
License-File: LICENSE
Requires-Dist: loguru>=0.6.0
Requires-Dist: pytz>=2021.1
Dynamic: author
Dynamic: author-email
Dynamic: classifier
Dynamic: description
Dynamic: description-content-type
Dynamic: home-page
Dynamic: keywords
Dynamic: license-file
Dynamic: requires-dist
Dynamic: requires-python
Dynamic: summary
